skytable_py/__init__.py
skytable_py/config.py
skytable_py/connection.py
skytable_py/exception.py
skytable_py/protocol.py
skytable_py/query.py
skytable_py/response.py
skytable_py-0.1.3.dist-info/METADATA
skytable_py-0.1.3.dist-info/WHEEL
skytable_py-0.1.3.dist-info/licenses/LICENSE
skytable_py-0.1.3.dist-info/RECORD
