Metadata-Version: 2.3
Name: skytable-py
Version: 0.1.3
Summary: Official Skytable client library for Python
Project-URL: Homepage, https://github.com/skytable/skytable-py
Project-URL: Issues, https://github.com/skytable/skytable-py/issues
Author-email: Sayan Nandan <nandansayan@outlook.com>
License-File: LICENSE
Classifier: License :: OSI Approved :: Apache Software License
Classifier: Operating System :: OS Independent
Classifier: Programming Language :: Python :: 3
Classifier: Topic :: Database
Classifier: Topic :: Database :: Database Engines/Servers
Classifier: Topic :: Database :: Front-Ends
Requires-Python: >=3.8
